genial/GenomeAnnotation.py
genial/__init__.py
genial/exceptions.py
genial/utils.py
genial/gff/__init__.py
genial/gff/attrib_parser.py
genial/gff/classes.py
genial/gff/line_parser.py
genial-0.1.0a1.data/scripts/annotMergeSmallGaps.py
genial-0.1.0a1.data/scripts/annotParser.py
genial-0.1.0a1.dist-info/DESCRIPTION.rst
genial-0.1.0a1.dist-info/METADATA
genial-0.1.0a1.dist-info/RECORD
genial-0.1.0a1.dist-info/WHEEL
genial-0.1.0a1.dist-info/metadata.json
genial-0.1.0a1.dist-info/top_level.txt
