Metadata-Version: 2.0
Name: genial
Version: 0.1.0a1
Summary: GENome Interactive Annotation Library
Home-page: https://github.com/varnion/genial
Author: Bruno F Souza
Author-email: fsouza.bruno@gmail.com
License: BSD
Platform: UNKNOWN
Classifier: Development Status :: 3 - Alpha
Classifier: Intended Audience :: Science/Research
Classifier: License :: OSI Approved :: BSD License
Classifier: Topic :: Scientific/Engineering :: Bio-Informatics
Classifier: Programming Language :: Python
Classifier: Programming Language :: Python :: 3
Classifier: Programming Language :: Python :: 3.5
Classifier: Topic :: Software Development :: Libraries :: Python Modules
Requires-Dist: numpy
Requires-Dist: pandas
Requires-Dist: python-magic (>=0.4.12)
